fuzzy_asteroids/__init__.py
fuzzy_asteroids/dashboard.py
fuzzy_asteroids/fuzzy_asteroids.py
fuzzy_asteroids/fuzzy_controller.py
fuzzy_asteroids/game.py
fuzzy_asteroids/runner.py
fuzzy_asteroids/settings.py
fuzzy_asteroids/sprites.py
fuzzy_asteroids/util.py
fuzzy_asteroids-3.3.1.dist-info/LICENSE
fuzzy_asteroids-3.3.1.dist-info/METADATA
fuzzy_asteroids-3.3.1.dist-info/WHEEL
fuzzy_asteroids-3.3.1.dist-info/top_level.txt
fuzzy_asteroids-3.3.1.dist-info/zip-safe
fuzzy_asteroids-3.3.1.dist-info/RECORD
