Metadata-Version: 2.1
Name: fuzzy-asteroids
Version: 3.3.1
Summary: Explainable Fuzzy Challenge - Asteroids Simulation Environment
Home-page: https://github.com/xfuzzycomp/FuzzyAsteroids
Author: Timothy Arnett
Author-email: tim.arnett@psibernetix.com
Maintainer: Timothy Arnett
Maintainer-email: tim.arnett@psibernetix.com
License: MIT License
Keywords: fuzzy logic,artificial intelligence,asteroids
Platform: UNKNOWN
Classifier: Programming Language :: Python :: 3
Classifier: Topic :: Scientific/Engineering :: Artificial Intelligence
Classifier: Operating System :: OS Independent
Requires-Python: >=3.6
License-File: LICENSE
Requires-Dist: arcade (==2.6.16)
